vref_utils/__init__.py
vref_utils/book_lists.py
vref_utils/verse.py
vref_utils/verse_list.py
vref_utils/versification.py
vref_utils/vref.py
vref_utils/vref.txt
vref_utils-0.0.10.dist-info/licenses/LICENSE
vref_utils-0.0.10.dist-info/METADATA
vref_utils-0.0.10.dist-info/WHEEL
vref_utils-0.0.10.dist-info/top_level.txt
vref_utils-0.0.10.dist-info/RECORD
