Metadata-Version: 2.4
Name: vref_utils
Version: 0.0.10
Summary: Tools to work with vref files (e.g., in the ebible corpus)
Home-page: https://github.com/jcuenod/vref_utils
Author: James Cuénod
Author-email: j3frea+github@gmail.com
License: MIT
Classifier: Programming Language :: Python :: 3
Classifier: License :: OSI Approved :: MIT License
Classifier: Operating System :: OS Independent
Requires-Python: >=3.8
License-File: LICENSE
Dynamic: author
Dynamic: author-email
Dynamic: classifier
Dynamic: description
Dynamic: description-content-type
Dynamic: home-page
Dynamic: license
Dynamic: license-file
Dynamic: requires-python
Dynamic: summary
